[{ "id": "Introduction", "parent" : "#", "text": "Introduction", "a_attr": {"href": "Introduction.html"}  },{ "id": "Welcome", "parent" : "Introduction", "text": "Welcome", "a_attr": {"href": "Welcome.html"}  },{ "id": "Whatsnew", "parent" : "Introduction", "text": "What's new", "a_attr": {"href": "Whatsnew.html"}  },{ "id": "GettingStarted", "parent" : "#", "text": "Getting Started", "a_attr": {"href": "GettingStarted.html"}  },{ "id": "Systemrequirements", "parent" : "GettingStarted", "text": "System requirements", "a_attr": {"href": "Systemrequirements.html"}  },{ "id": "Gettinghelp", "parent" : "GettingStarted", "text": "Getting help", "a_attr": {"href": "Gettinghelp.html"}  },{ "id": "Classes", "parent" : "#", "text": "Classes", "a_attr": {"href": "Classes.html"} , "icon": "icon-0" },{ "id": "ClassList", "parent" : "Classes", "text": "Class List", "a_attr": {"href": "ClassList.html"} , "icon": "icon-0" },{ "id": "AbstractLegend", "parent" : "ClassList", "text": "AbstractLegend", "a_attr": {"href": "AbstractLegend.html"}  },{ "id": "AbstractScaleDraw", "parent" : "ClassList", "text": "AbstractScaleDraw", "a_attr": {"href": "AbstractScaleDraw.html"}  },{ "id": "ColorMap", "parent" : "ClassList", "text": "ColorMap", "a_attr": {"href": "ColorMap.html"}  },{ "id": "CurveFitter", "parent" : "ClassList", "text": "CurveFitter", "a_attr": {"href": "CurveFitter.html"}  },{ "id": "EventPattern", "parent" : "ClassList", "text": "EventPattern", "a_attr": {"href": "EventPattern.html"}  },{ "id": "Graphic", "parent" : "ClassList", "text": "Graphic", "a_attr": {"href": "Graphic.html"}  },{ "id": "hObject", "parent" : "ClassList", "text": "hObject", "a_attr": {"href": "hObject.html"}  },{ "id": "Interval", "parent" : "ClassList", "text": "Interval", "a_attr": {"href": "Interval.html"}  },{ "id": "Legend", "parent" : "ClassList", "text": "Legend", "a_attr": {"href": "Legend.html"}  },{ "id": "LegendData", "parent" : "ClassList", "text": "LegendData", "a_attr": {"href": "LegendData.html"}  },{ "id": "LegendLabel", "parent" : "ClassList", "text": "LegendLabel", "a_attr": {"href": "LegendLabel.html"}  },{ "id": "LinearColorMap", "parent" : "ClassList", "text": "LinearColorMap", "a_attr": {"href": "LinearColorMap.html"}  },{ "id": "LinearScaleEngine", "parent" : "ClassList", "text": "LinearScaleEngine", "a_attr": {"href": "LinearScaleEngine.html"}  },{ "id": "LogScaleEngine", "parent" : "ClassList", "text": "LogScaleEngine", "a_attr": {"href": "LogScaleEngine.html"}  },{ "id": "LogTransform", "parent" : "ClassList", "text": "LogTransform", "a_attr": {"href": "LogTransform.html"}  },{ "id": "Magnifier", "parent" : "ClassList", "text": "Magnifier", "a_attr": {"href": "Magnifier.html"}  },{ "id": "NullTransform", "parent" : "ClassList", "text": "NullTransform", "a_attr": {"href": "NullTransform.html"}  },{ "id": "Painter", "parent" : "ClassList", "text": "Painter", "a_attr": {"href": "Painter.html"}  },{ "id": "Panner", "parent" : "ClassList", "text": "Panner", "a_attr": {"href": "Panner.html"}  },{ "id": "Picker", "parent" : "ClassList", "text": "Picker", "a_attr": {"href": "Picker.html"}  },{ "id": "PickerClickPointMachine", "parent" : "ClassList", "text": "PickerClickPointMachine", "a_attr": {"href": "PickerClickPointMachine.html"}  },{ "id": "PickerClickRectMachine", "parent" : "ClassList", "text": "PickerClickRectMachine", "a_attr": {"href": "PickerClickRectMachine.html"}  },{ "id": "PickerDragLineMachine", "parent" : "ClassList", "text": "PickerDragLineMachine", "a_attr": {"href": "PickerDragLineMachine.html"}  },{ "id": "PickerDragPointMachine", "parent" : "ClassList", "text": "PickerDragPointMachine", "a_attr": {"href": "PickerDragPointMachine.html"}  },{ "id": "PickerDragRectMachine", "parent" : "ClassList", "text": "PickerDragRectMachine", "a_attr": {"href": "PickerDragRectMachine.html"}  },{ "id": "PickerMachine", "parent" : "ClassList", "text": "PickerMachine", "a_attr": {"href": "PickerMachine.html"}  },{ "id": "PickerPolygonMachine", "parent" : "ClassList", "text": "PickerPolygonMachine", "a_attr": {"href": "PickerPolygonMachine.html"}  },{ "id": "PickerTrackerMachine", "parent" : "ClassList", "text": "PickerTrackerMachine", "a_attr": {"href": "PickerTrackerMachine.html"}  },{ "id": "Plot", "parent" : "ClassList", "text": "Plot", "a_attr": {"href": "Plot.html"}  },{ "id": "PlotCanvas", "parent" : "ClassList", "text": "PlotCanvas", "a_attr": {"href": "PlotCanvas.html"}  },{ "id": "PlotCurve", "parent" : "ClassList", "text": "PlotCurve", "a_attr": {"href": "PlotCurve.html"}  },{ "id": "PlotDict", "parent" : "ClassList", "text": "PlotDict", "a_attr": {"href": "PlotDict.html"}  },{ "id": "PlotGrid", "parent" : "ClassList", "text": "PlotGrid", "a_attr": {"href": "PlotGrid.html"}  },{ "id": "PlotItem", "parent" : "ClassList", "text": "PlotItem", "a_attr": {"href": "PlotItem.html"}  },{ "id": "Layout", "parent" : "ClassList", "text": "Layout", "a_attr": {"href": "Layout.html"}  },{ "id": "LegendItem", "parent" : "ClassList", "text": "LegendItem", "a_attr": {"href": "LegendItem.html"}  },{ "id": "PlotMarker", "parent" : "ClassList", "text": "PlotMarker", "a_attr": {"href": "PlotMarker.html"}  },{ "id": "PlotPicker", "parent" : "ClassList", "text": "PlotPicker", "a_attr": {"href": "PlotPicker.html"}  },{ "id": "PlotScaleItem", "parent" : "ClassList", "text": "PlotScaleItem", "a_attr": {"href": "PlotScaleItem.html"}  },{ "id": "PlotSeriesItem", "parent" : "ClassList", "text": "PlotSeriesItem", "a_attr": {"href": "PlotSeriesItem.html"}  },{ "id": "PlotShapeItem", "parent" : "ClassList", "text": "PlotShapeItem", "a_attr": {"href": "PlotShapeItem.html"}  },{ "id": "PlotSpectroCurve", "parent" : "ClassList", "text": "PlotSpectroCurve", "a_attr": {"href": "PlotSpectroCurve.html"}  },{ "id": "PlotSpectrogram", "parent" : "ClassList", "text": "PlotSpectrogram", "a_attr": {"href": "PlotSpectrogram.html"}  },{ "id": "PlotZoneItem", "parent" : "ClassList", "text": "PlotZoneItem", "a_attr": {"href": "PlotZoneItem.html"}  },{ "id": "PlotZoomer", "parent" : "ClassList", "text": "PlotZoomer", "a_attr": {"href": "PlotZoomer.html"}  },{ "id": "PointMapper", "parent" : "ClassList", "text": "PointMapper", "a_attr": {"href": "PointMapper.html"}  },{ "id": "PointSeriesData", "parent" : "ClassList", "text": "PointSeriesData", "a_attr": {"href": "PointSeriesData.html"}  },{ "id": "PowerTransform", "parent" : "ClassList", "text": "PowerTransform", "a_attr": {"href": "PowerTransform.html"}  },{ "id": "ScaleDiv", "parent" : "ClassList", "text": "ScaleDiv", "a_attr": {"href": "ScaleDiv.html"}  },{ "id": "ScaleDraw", "parent" : "ClassList", "text": "ScaleDraw", "a_attr": {"href": "ScaleDraw.html"}  },{ "id": "ScaleEngine", "parent" : "ClassList", "text": "ScaleEngine", "a_attr": {"href": "ScaleEngine.html"}  },{ "id": "ScaleMap", "parent" : "ClassList", "text": "ScaleMap", "a_attr": {"href": "ScaleMap.html"}  },{ "id": "ScaleWidget", "parent" : "ClassList", "text": "ScaleWidget", "a_attr": {"href": "ScaleWidget.html"}  },{ "id": "SeriesData", "parent" : "ClassList", "text": "SeriesData", "a_attr": {"href": "SeriesData.html"}  },{ "id": "Spline", "parent" : "ClassList", "text": "Spline", "a_attr": {"href": "Spline.html"}  },{ "id": "SplineCurveFitter", "parent" : "ClassList", "text": "SplineCurveFitter", "a_attr": {"href": "SplineCurveFitter.html"}  },{ "id": "Symbol", "parent" : "ClassList", "text": "Symbol", "a_attr": {"href": "Symbol.html"}  },{ "id": "SyntheticPointData", "parent" : "ClassList", "text": "SyntheticPointData", "a_attr": {"href": "SyntheticPointData.html"}  },{ "id": "Transform", "parent" : "ClassList", "text": "Transform", "a_attr": {"href": "Transform.html"}  },{ "id": "WeedingCurveFitter", "parent" : "ClassList", "text": "WeedingCurveFitter", "a_attr": {"href": "WeedingCurveFitter.html"}  },{ "id": "WidgetOverlay", "parent" : "ClassList", "text": "WidgetOverlay", "a_attr": {"href": "WidgetOverlay.html"}  }]